Metadata-Version: 2.0
Name: odoo9-addon-website-canonical-url
Version: 9.0.1.1.0
Summary: Canonical URL in Website Headers
Home-page: http://www.initos.com
Author: initOS GmbH, Tecnativa, Odoo Community Association (OCA)
Author-email: support@odoo-community.org
License: AGPL-3
Platform: UNKNOWN
Requires-Dist: odoo (<9.1a,>=9.0a)
Classifier: Programming Language :: Python :: 2.7
Classifier: Framework :: Odoo
Classifier: License :: OSI Approved :: GNU Affero General Public License v3
